{
 "img": "particles.png",
 "sprites": [
  {
   "key": "b_0",
   "x": 0,
   "y": 0,
   "h": 2,
   "w": 2
  },
  {
   "key": "b_1",
   "x": 2,
   "y": 0,
   "h": 2,
   "w": 2
  },
  {
   "key": "b_2",
   "x": 4,
   "y": 0,
   "h": 2,
   "w": 2
  },
  {
   "key": "b_3",
   "x": 6,
   "y": 0,
   "h": 2,
   "w": 2
  },
  {
   "key": "b_4",
   "x": 0,
   "y": 2,
   "h": 5,
   "w": 4
  },
  {
   "key": "b_5",
   "x": 4,
   "y": 2,
   "h": 3,
   "w": 3
  },
  {
   "key": "b_6",
   "x": 7,
   "y": 2,
   "h": 4,
   "w": 4
  },
  {
   "key": "b_7",
   "x": 11,
   "y": 2,
   "h": 5,
   "w": 5
  },
  {
   "key": "b_8",
   "x": 0,
   "y": 0,
   "h": 64,
   "w": 64
  }
 ]
}
